bin/__init__.py
bin/djangoloadbalancer.py
django_load_balancer/__init__.py
django_load_balancer/database.py
django_load_balancer/executor.py
django_load_balancer/info_query_executor.py
django_load_balancer/load_balancer.py
django_load_balancer/load_balancer_factory.py
django_load_balancer/load_balancer_model.py
django_load_balancer/local_settings.py
django_load_balancer/query.py
django_load_balancer/waiter.py
django_load_balancer/watch_dog.py
django_load_balancer/balancing_algorithms/__init__.py
django_load_balancer/balancing_algorithms/cud_algorithm.py
django_load_balancer/balancing_algorithms/r_algorithm.py
django_load_balancer/balancing_algorithms/cud_algorithms/__init__.py
django_load_balancer/balancing_algorithms/cud_algorithms/multithreading.py
django_load_balancer/balancing_algorithms/r_algorithms/__init__.py
django_load_balancer/balancing_algorithms/r_algorithms/interval.py
django_load_balancer/balancing_algorithms/r_algorithms/round_robin.py
django_load_balancer/management/__init__.py
django_load_balancer/management/commands/__init__.py
django_load_balancer/management/commands/runserver.py
djangoloadbalancer-0.0.56.data/scripts/djangoloadbalancer.py
djangoloadbalancer-0.0.56.dist-info/METADATA
djangoloadbalancer-0.0.56.dist-info/WHEEL
djangoloadbalancer-0.0.56.dist-info/top_level.txt
djangoloadbalancer-0.0.56.dist-info/RECORD
