Metadata-Version: 2.1
Name: djangoloadbalancer
Version: 0.0.56
Summary: Package enabling to load balance requests to databases in django projects
Home-page: https://github.com/DanielKlarenbach/DjangoLoadBalancer
Author: Daniel Klarenbach
License: Apache License 2.0
Platform: UNKNOWN
